<annotation>
	<folder>dataset_prueba1</folder>
	<filename>Categoría_Perspectiva_Cenital_y_Minimización_de_Oclusión_29.jpg</filename>
	<path>C:\Users\Tatto\OneDrive\Documentos\Metodos y procesamiento de imagenes\Proyecto\semaforo_entrenar\dataset_prueba1\Categoría_Perspectiva_Cenital_y_Minimización_de_Oclusión_29.jpg</path>
	<source>
		<database>Unknown</database>
	</source>
	<size>
		<width>640</width>
		<height>640</height>
		<depth>3</depth>
	</size>
	<segmented>0</segmented>
	<object>
		<name>car</name>
		<pose>Unspecified</pose>
		<truncated>0</truncated>
		<difficult>0</difficult>
		<bndbox>
			<xmin>247</xmin>
			<ymin>289</ymin>
			<xmax>414</xmax>
			<ymax>576</ymax>
		</bndbox>
	</object>
	<object>
		<name>car</name>
		<pose>Unspecified</pose>
		<truncated>0</truncated>
		<difficult>0</difficult>
		<bndbox>
			<xmin>429</xmin>
			<ymin>360</ymin>
			<xmax>603</xmax>
			<ymax>636</ymax>
		</bndbox>
	</object>
	<object>
		<name>car</name>
		<pose>Unspecified</pose>
		<truncated>0</truncated>
		<difficult>0</difficult>
		<bndbox>
			<xmin>438</xmin>
			<ymin>177</ymin>
			<xmax>515</xmax>
			<ymax>319</ymax>
		</bndbox>
	</object>
	<object>
		<name>car</name>
		<pose>Unspecified</pose>
		<truncated>0</truncated>
		<difficult>0</difficult>
		<bndbox>
			<xmin>470</xmin>
			<ymin>142</ymin>
			<xmax>516</xmax>
			<ymax>203</ymax>
		</bndbox>
	</object>
	<object>
		<name>car</name>
		<pose>Unspecified</pose>
		<truncated>0</truncated>
		<difficult>0</difficult>
		<bndbox>
			<xmin>448</xmin>
			<ymin>44</ymin>
			<xmax>469</xmax>
			<ymax>66</ymax>
		</bndbox>
	</object>
</annotation>
