<annotation>
	<folder>imagenes</folder>
	<filename>Escenarios_de_Iluminación_Homogénea_101.jpg</filename>
	<path>C:\Users\Tatto\OneDrive\Documentos\Metodos y procesamiento de imagenes\Proyecto\semaforo_entrenar\dataset_dividido\entrenamiento\imagenes\Escenarios_de_Iluminación_Homogénea_101.jpg</path>
	<source>
		<database>Unknown</database>
	</source>
	<size>
		<width>1920</width>
		<height>1080</height>
		<depth>3</depth>
	</size>
	<segmented>0</segmented>
	<object>
		<name>car</name>
		<pose>Unspecified</pose>
		<truncated>0</truncated>
		<difficult>0</difficult>
		<bndbox>
			<xmin>1684</xmin>
			<ymin>226</ymin>
			<xmax>1902</xmax>
			<ymax>398</ymax>
		</bndbox>
	</object>
	<object>
		<name>car</name>
		<pose>Unspecified</pose>
		<truncated>0</truncated>
		<difficult>0</difficult>
		<bndbox>
			<xmin>1401</xmin>
			<ymin>194</ymin>
			<xmax>1546</xmax>
			<ymax>296</ymax>
		</bndbox>
	</object>
	<object>
		<name>car</name>
		<pose>Unspecified</pose>
		<truncated>0</truncated>
		<difficult>0</difficult>
		<bndbox>
			<xmin>944</xmin>
			<ymin>249</ymin>
			<xmax>1107</xmax>
			<ymax>355</ymax>
		</bndbox>
	</object>
	<object>
		<name>car</name>
		<pose>Unspecified</pose>
		<truncated>0</truncated>
		<difficult>0</difficult>
		<bndbox>
			<xmin>1154</xmin>
			<ymin>225</ymin>
			<xmax>1332</xmax>
			<ymax>325</ymax>
		</bndbox>
	</object>
	<object>
		<name>motorbike</name>
		<pose>Unspecified</pose>
		<truncated>0</truncated>
		<difficult>0</difficult>
		<bndbox>
			<xmin>254</xmin>
			<ymin>420</ymin>
			<xmax>352</xmax>
			<ymax>518</ymax>
		</bndbox>
	</object>
	<object>
		<name>car</name>
		<pose>Unspecified</pose>
		<truncated>0</truncated>
		<difficult>0</difficult>
		<bndbox>
			<xmin>3</xmin>
			<ymin>480</ymin>
			<xmax>124</xmax>
			<ymax>608</ymax>
		</bndbox>
	</object>
	<object>
		<name>motorbike</name>
		<pose>Unspecified</pose>
		<truncated>0</truncated>
		<difficult>0</difficult>
		<bndbox>
			<xmin>140</xmin>
			<ymin>429</ymin>
			<xmax>209</xmax>
			<ymax>504</ymax>
		</bndbox>
	</object>
	<object>
		<name>motorbike</name>
		<pose>Unspecified</pose>
		<truncated>0</truncated>
		<difficult>0</difficult>
		<bndbox>
			<xmin>520</xmin>
			<ymin>325</ymin>
			<xmax>607</xmax>
			<ymax>416</ymax>
		</bndbox>
	</object>
	<object>
		<name>car</name>
		<pose>Unspecified</pose>
		<truncated>0</truncated>
		<difficult>0</difficult>
		<bndbox>
			<xmin>591</xmin>
			<ymin>273</ymin>
			<xmax>787</xmax>
			<ymax>376</ymax>
		</bndbox>
	</object>
	<object>
		<name>car</name>
		<pose>Unspecified</pose>
		<truncated>0</truncated>
		<difficult>0</difficult>
		<bndbox>
			<xmin>742</xmin>
			<ymin>237</ymin>
			<xmax>828</xmax>
			<ymax>306</ymax>
		</bndbox>
	</object>
	<object>
		<name>person</name>
		<pose>Unspecified</pose>
		<truncated>0</truncated>
		<difficult>0</difficult>
		<bndbox>
			<xmin>289</xmin>
			<ymin>655</ymin>
			<xmax>409</xmax>
			<ymax>861</ymax>
		</bndbox>
	</object>
	<object>
		<name>motorbike</name>
		<pose>Unspecified</pose>
		<truncated>0</truncated>
		<difficult>0</difficult>
		<bndbox>
			<xmin>974</xmin>
			<ymin>195</ymin>
			<xmax>1011</xmax>
			<ymax>249</ymax>
		</bndbox>
	</object>
	<object>
		<name>motorbike</name>
		<pose>Unspecified</pose>
		<truncated>0</truncated>
		<difficult>0</difficult>
		<bndbox>
			<xmin>909</xmin>
			<ymin>226</ymin>
			<xmax>950</xmax>
			<ymax>301</ymax>
		</bndbox>
	</object>
	<object>
		<name>motorbike</name>
		<pose>Unspecified</pose>
		<truncated>0</truncated>
		<difficult>0</difficult>
		<bndbox>
			<xmin>932</xmin>
			<ymin>237</ymin>
			<xmax>992</xmax>
			<ymax>315</ymax>
		</bndbox>
	</object>
	<object>
		<name>bus</name>
		<pose>Unspecified</pose>
		<truncated>0</truncated>
		<difficult>0</difficult>
		<bndbox>
			<xmin>1121</xmin>
			<ymin>132</ymin>
			<xmax>1265</xmax>
			<ymax>204</ymax>
		</bndbox>
	</object>
	<object>
		<name>car</name>
		<pose>Unspecified</pose>
		<truncated>0</truncated>
		<difficult>0</difficult>
		<bndbox>
			<xmin>1258</xmin>
			<ymin>181</ymin>
			<xmax>1395</xmax>
			<ymax>237</ymax>
		</bndbox>
	</object>
	<object>
		<name>car</name>
		<pose>Unspecified</pose>
		<truncated>0</truncated>
		<difficult>0</difficult>
		<bndbox>
			<xmin>1059</xmin>
			<ymin>208</ymin>
			<xmax>1170</xmax>
			<ymax>276</ymax>
		</bndbox>
	</object>
	<object>
		<name>motorbike</name>
		<pose>Unspecified</pose>
		<truncated>0</truncated>
		<difficult>0</difficult>
		<bndbox>
			<xmin>1607</xmin>
			<ymin>201</ymin>
			<xmax>1668</xmax>
			<ymax>284</ymax>
		</bndbox>
	</object>
	<object>
		<name>car</name>
		<pose>Unspecified</pose>
		<truncated>0</truncated>
		<difficult>0</difficult>
		<bndbox>
			<xmin>1724</xmin>
			<ymin>178</ymin>
			<xmax>1803</xmax>
			<ymax>243</ymax>
		</bndbox>
	</object>
	<object>
		<name>motorbike</name>
		<pose>Unspecified</pose>
		<truncated>1</truncated>
		<difficult>0</difficult>
		<bndbox>
			<xmin>1213</xmin>
			<ymin>769</ymin>
			<xmax>1557</xmax>
			<ymax>1080</ymax>
		</bndbox>
	</object>
</annotation>
