<annotation>
	<folder>imagenes</folder>
	<filename>Flujo_Vehicular_y_Clasificación_Multiclase_45.jpeg</filename>
	<path>C:\Users\Admin\Desktop\semaforo\semaforo_entrenar\dataset_dividido\entrenamiento\imagenes\Flujo_Vehicular_y_Clasificación_Multiclase_45.jpeg</path>
	<source>
		<database>Unknown</database>
	</source>
	<size>
		<width>1080</width>
		<height>608</height>
		<depth>3</depth>
	</size>
	<segmented>0</segmented>
	<object>
		<name>car</name>
		<pose>Unspecified</pose>
		<truncated>0</truncated>
		<difficult>0</difficult>
		<bndbox>
			<xmin>164</xmin>
			<ymin>234</ymin>
			<xmax>477</xmax>
			<ymax>483</ymax>
		</bndbox>
	</object>
	<object>
		<name>bus</name>
		<pose>Unspecified</pose>
		<truncated>0</truncated>
		<difficult>0</difficult>
		<bndbox>
			<xmin>282</xmin>
			<ymin>68</ymin>
			<xmax>610</xmax>
			<ymax>241</ymax>
		</bndbox>
	</object>
	<object>
		<name>person</name>
		<pose>Unspecified</pose>
		<truncated>0</truncated>
		<difficult>0</difficult>
		<bndbox>
			<xmin>744</xmin>
			<ymin>312</ymin>
			<xmax>825</xmax>
			<ymax>437</ymax>
		</bndbox>
	</object>
	<object>
		<name>car</name>
		<pose>Unspecified</pose>
		<truncated>0</truncated>
		<difficult>0</difficult>
		<bndbox>
			<xmin>957</xmin>
			<ymin>136</ymin>
			<xmax>1078</xmax>
			<ymax>212</ymax>
		</bndbox>
	</object>
	<object>
		<name>car</name>
		<pose>Unspecified</pose>
		<truncated>0</truncated>
		<difficult>0</difficult>
		<bndbox>
			<xmin>833</xmin>
			<ymin>104</ymin>
			<xmax>910</xmax>
			<ymax>162</ymax>
		</bndbox>
	</object>
	<object>
		<name>motorbike</name>
		<pose>Unspecified</pose>
		<truncated>0</truncated>
		<difficult>0</difficult>
		<bndbox>
			<xmin>189</xmin>
			<ymin>196</ymin>
			<xmax>302</xmax>
			<ymax>282</ymax>
		</bndbox>
	</object>
	<object>
		<name>motorbike</name>
		<pose>Unspecified</pose>
		<truncated>0</truncated>
		<difficult>0</difficult>
		<bndbox>
			<xmin>815</xmin>
			<ymin>159</ymin>
			<xmax>862</xmax>
			<ymax>237</ymax>
		</bndbox>
	</object>
	<object>
		<name>motorbike</name>
		<pose>Unspecified</pose>
		<truncated>0</truncated>
		<difficult>0</difficult>
		<bndbox>
			<xmin>575</xmin>
			<ymin>130</ymin>
			<xmax>634</xmax>
			<ymax>176</ymax>
		</bndbox>
	</object>
	<object>
		<name>person</name>
		<pose>Unspecified</pose>
		<truncated>0</truncated>
		<difficult>0</difficult>
		<bndbox>
			<xmin>982</xmin>
			<ymin>315</ymin>
			<xmax>1054</xmax>
			<ymax>455</ymax>
		</bndbox>
	</object>
	<object>
		<name>person</name>
		<pose>Unspecified</pose>
		<truncated>0</truncated>
		<difficult>0</difficult>
		<bndbox>
			<xmin>32</xmin>
			<ymin>215</ymin>
			<xmax>144</xmax>
			<ymax>306</ymax>
		</bndbox>
	</object>
	<object>
		<name>person</name>
		<pose>Unspecified</pose>
		<truncated>0</truncated>
		<difficult>0</difficult>
		<bndbox>
			<xmin>140</xmin>
			<ymin>124</ymin>
			<xmax>167</xmax>
			<ymax>188</ymax>
		</bndbox>
	</object>
	<object>
		<name>person</name>
		<pose>Unspecified</pose>
		<truncated>0</truncated>
		<difficult>0</difficult>
		<bndbox>
			<xmin>165</xmin>
			<ymin>125</ymin>
			<xmax>199</xmax>
			<ymax>188</ymax>
		</bndbox>
	</object>
	<object>
		<name>person</name>
		<pose>Unspecified</pose>
		<truncated>0</truncated>
		<difficult>0</difficult>
		<bndbox>
			<xmin>198</xmin>
			<ymin>121</ymin>
			<xmax>241</xmax>
			<ymax>188</ymax>
		</bndbox>
	</object>
</annotation>
