<annotation>
	<folder>imagenes</folder>
	<filename>Flujo_Vehicular_y_Clasificación_Multiclase_136.jpeg</filename>
	<path>C:\Users\Admin\Desktop\semaforo\semaforo_entrenar\dataset_dividido\validacion\imagenes\Flujo_Vehicular_y_Clasificación_Multiclase_136.jpeg</path>
	<source>
		<database>Unknown</database>
	</source>
	<size>
		<width>640</width>
		<height>409</height>
		<depth>3</depth>
	</size>
	<segmented>0</segmented>
	<object>
		<name>bus</name>
		<pose>Unspecified</pose>
		<truncated>0</truncated>
		<difficult>0</difficult>
		<bndbox>
			<xmin>457</xmin>
			<ymin>19</ymin>
			<xmax>581</xmax>
			<ymax>125</ymax>
		</bndbox>
	</object>
	<object>
		<name>car</name>
		<pose>Unspecified</pose>
		<truncated>0</truncated>
		<difficult>0</difficult>
		<bndbox>
			<xmin>352</xmin>
			<ymin>4</ymin>
			<xmax>467</xmax>
			<ymax>101</ymax>
		</bndbox>
	</object>
	<object>
		<name>person</name>
		<pose>Unspecified</pose>
		<truncated>0</truncated>
		<difficult>0</difficult>
		<bndbox>
			<xmin>368</xmin>
			<ymin>261</ymin>
			<xmax>452</xmax>
			<ymax>357</ymax>
		</bndbox>
	</object>
	<object>
		<name>car</name>
		<pose>Unspecified</pose>
		<truncated>0</truncated>
		<difficult>0</difficult>
		<bndbox>
			<xmin>187</xmin>
			<ymin>153</ymin>
			<xmax>322</xmax>
			<ymax>269</ymax>
		</bndbox>
	</object>
	<object>
		<name>bus</name>
		<pose>Unspecified</pose>
		<truncated>0</truncated>
		<difficult>0</difficult>
		<bndbox>
			<xmin>187</xmin>
			<ymin>146</ymin>
			<xmax>320</xmax>
			<ymax>267</ymax>
		</bndbox>
	</object>
	<object>
		<name>bus</name>
		<pose>Unspecified</pose>
		<truncated>0</truncated>
		<difficult>0</difficult>
		<bndbox>
			<xmin>350</xmin>
			<ymin>3</ymin>
			<xmax>467</xmax>
			<ymax>99</ymax>
		</bndbox>
	</object>
	<object>
		<name>car</name>
		<pose>Unspecified</pose>
		<truncated>0</truncated>
		<difficult>0</difficult>
		<bndbox>
			<xmin>351</xmin>
			<ymin>128</ymin>
			<xmax>477</xmax>
			<ymax>248</ymax>
		</bndbox>
	</object>
	<object>
		<name>person</name>
		<pose>Unspecified</pose>
		<truncated>0</truncated>
		<difficult>0</difficult>
		<bndbox>
			<xmin>151</xmin>
			<ymin>284</ymin>
			<xmax>205</xmax>
			<ymax>380</ymax>
		</bndbox>
	</object>
	<object>
		<name>person</name>
		<pose>Unspecified</pose>
		<truncated>0</truncated>
		<difficult>0</difficult>
		<bndbox>
			<xmin>267</xmin>
			<ymin>282</ymin>
			<xmax>321</xmax>
			<ymax>372</ymax>
		</bndbox>
	</object>
	<object>
		<name>person</name>
		<pose>Unspecified</pose>
		<truncated>0</truncated>
		<difficult>0</difficult>
		<bndbox>
			<xmin>358</xmin>
			<ymin>260</ymin>
			<xmax>410</xmax>
			<ymax>360</ymax>
		</bndbox>
	</object>
</annotation>
